pygame/__init__.py
pygame/collisions.py
pygame/hitboxes.py
pygame/others.py
setton/MRU.py
setton/Music.py
setton/Tones.py
setton/__init__.py
setton/constantes.py
setton/jogos_de_sorte.py
setton/manipulacao_de_arquivos.py
setton/matematica.py
setton/utils.py
setton/Pygame/__init__.py
setton/Pygame/collisions.py
setton/Pygame/hitboxes.py
setton/Pygame/others.py
setton-2.0.dist-info/LICENSE
setton-2.0.dist-info/METADATA
setton-2.0.dist-info/WHEEL
setton-2.0.dist-info/top_level.txt
setton-2.0.dist-info/RECORD
