Metadata-Version: 2.1
Name: setton
Version: 2.0
Summary: Algumas Funções úteis para diversas coisas
Home-page: https://github.com/RafaelSetton/setton
Author: Rafael Setton
Author-email: rasealca2017@gmail.com
License: UNKNOWN
Platform: UNKNOWN
Classifier: Programming Language :: Python :: 3
Classifier: License :: OSI Approved :: MIT License
Classifier: Operating System :: OS Independent
Requires-Python: >=3.6
